vismap/__init__.py
vismap/_version.py
vismap/canvas.py
vismap/cat-killer-256x256.png
vismap/fs_cache.py
vismap/tile_providers.py
vismap/transforms.py
vismap/view.py
vismap/examples/__init__.py
vismap/examples/basic.py
vismap/examples/grid.py
vismap/scripts/__init__.py
vismap/scripts/cache_up.py
vismap-0.2.1.dist-info/LICENSE
vismap-0.2.1.dist-info/METADATA
vismap-0.2.1.dist-info/WHEEL
vismap-0.2.1.dist-info/entry_points.txt
vismap-0.2.1.dist-info/top_level.txt
vismap-0.2.1.dist-info/RECORD
