Metadata-Version: 2.1
Name: vismap
Version: 0.2.1
Summary: Tile maps rendered with Vispy
Home-page: https://github.com/codypiersall/vismap
Author: Cody Piersall
Author-email: cody.piersall@gmail.com
License: MIT
Keywords: vispy plot geography map
Platform: UNKNOWN
Classifier: Programming Language :: Python :: 3
Classifier: License :: OSI Approved :: MIT License
Classifier: Operating System :: OS Independent
Requires-Dist: numpy
Requires-Dist: vispy
Requires-Dist: mercantile
Requires-Dist: requests
Requires-Dist: requests-cache
Requires-Dist: pillow
